pyasciilib/__init__.py
pyasciilib/to_ascii.py
pyasciilib-1.0.2.dist-info/LICENSE
pyasciilib-1.0.2.dist-info/METADATA
pyasciilib-1.0.2.dist-info/WHEEL
pyasciilib-1.0.2.dist-info/entry_points.txt
pyasciilib-1.0.2.dist-info/top_level.txt
pyasciilib-1.0.2.dist-info/RECORD
