Metadata-Version: 2.1
Name: pyasciilib
Version: 1.0.2
Summary: A library to convert images to ASCII art using different methods
Home-page: https://github.com/Slinky802/pyasciilib
Author: Alexandre Poggioli
Author-email: alexandrepoggioli09@gmail.com
Classifier: Programming Language :: Python :: 3
Classifier: License :: OSI Approved :: MIT License
Classifier: Operating System :: OS Independent
Requires-Python: >=3.6
License-File: LICENSE
Requires-Dist: Pillow >=8.0.0
